CHANGES.rst
DESCRIPTION.rst
LICENSE
MANIFEST.in
README.md
setup.py
src/ldc_html/__init__.py
src/ldc_html/class_lister.py
src/ldc_html.egg-info/PKG-INFO
src/ldc_html.egg-info/SOURCES.txt
src/ldc_html.egg-info/dependency_links.txt
src/ldc_html.egg-info/entry_points.txt
src/ldc_html.egg-info/requires.txt
src/ldc_html.egg-info/top_level.txt
src/ldc_html/pretrain/__init__.py
src/ldc_html/pretrain/_html.py